[
  {
    "id": "rspb-skylark-8x32",
    "category": "binoculars",
    "brand": "RSPB",
    "model": "Skylark 8x32",
    "price_gbp": 90,
    "warranty": "1-year warranty",
    "value_for_money": "Affordable and lightweight entry-level binoculars",
    "weight_g": 450,
    "best_for": [
      "Entry level",
      "Beginners",
      "Travel"
    ],
    "image": "Images/skylark 8x32.jpg",
    "staff_notes": "",
    "specs": {
      "Magnification": "8x",
      "Objective lens diameter (mm)": "32",
      "ED lens": "No",
      "Close focus distance (m)": "3",
      "Field of view (degrees)": "7.4",
      "Field of view (m/1000m)": "130",
      "Eye relief (mm)": "16.8",
      "Exit pupil (mm)": "4",
      "Interpupillary distance (mm)": "53-72",
      "Waterproof": "Yes",
      "Nitrogen-filled": "Yes",
      "Weight (g)": "450",
      "Dimensions L x W x H (mm)": "120 x 120 x 50",
      "Warranty": "1 year"
    }
  },
  {
    "id": "rspb-skylark-8x42",
    "category": "binoculars",
    "brand": "RSPB",
    "model": "Skylark 8x42",
    "price_gbp": 100,
    "warranty": "1-year warranty",
    "value_for_money": "Affordable and reliable starter binoculars",
    "weight_g": 580,
    "best_for": [
      "Entry level",
      "All-round birding",
      "Beginners"
    ],
    "image": "Images/skylark 8x42.jpg",
    "staff_notes": "",
    "specs": {
      "Magnification": "8x",
      "Objective lens diameter (mm)": "42",
      "ED lens": "No",
      "Close focus distance (m)": "4.5",
      "Field of view (degrees)": "6.2",
      "Field of view (m/1000m)": "108",
      "Eye relief (mm)": "20.4",
      "Exit pupil (mm)": "5.25",
      "Interpupillary distance (mm)": "53-72",
      "Waterproof": "Yes",
      "Nitrogen-filled": "Yes",
      "Weight (g)": "580",
      "Dimensions L x W x H (mm)": "120 x 155 x 55",
      "Warranty": "1 year"
    }
  },
  {
    "id": "rspb-skylark-10x42",
    "category": "binoculars",
    "brand": "RSPB",
    "model": "Skylark 10x42",
    "price_gbp": 110,
    "warranty": "1-year warranty",
    "value_for_money": "Affordable entry-level option for longer reach",
    "weight_g": 580,
    "best_for": [
      "Entry level",
      "Open habitats",
      "Long distance"
    ],
    "image": "Images/skylark 10x42.jpg",
    "staff_notes": "",
    "specs": {
      "Magnification": "10x",
      "Objective lens diameter (mm)": "42",
      "ED lens": "No",
      "Close focus distance (m)": "4.5",
      "Field of view (degrees)": "5.8",
      "Field of view (m/1000m)": "101",
      "Eye relief (mm)": "16.9",
      "Exit pupil (mm)": "4.2",
      "Interpupillary distance (mm)": "53-72",
      "Waterproof": "Yes",
      "Nitrogen-filled": "Yes",
      "Weight (g)": "580",
      "Dimensions L x W x H (mm)": "120 x 155 x 55",
      "Warranty": "1 year"
    }
  },
  {
    "id": "rspb-asw-8x40",
    "category": "binoculars",
    "brand": "RSPB",
    "model": "ASW 8x40",
    "price_gbp": 160,
    "warranty": "5-year warranty",
    "value_for_money": "Traditional wide-field binoculars offering excellent value",
    "weight_g": 698,
    "best_for": [
      "Entry level",
      "Wide field of view",
      "General wildlife"
    ],
    "image": "Images/asw.jpg",
    "staff_notes": "",
    "specs": {
      "Magnification": "8",
      "Objective lens diameter (mm)": "40",
      "ED lens": "No",
      "Close focus distance": "4m",
      "Field of view (degrees)": "8.2",
      "Field of view (m/1000m)": "143",
      "Eye relief (mm)": "13",
      "Exit pupil (mm)": "5",
      "Waterproof": "No",
      "Nitrogen filled": "No",
      "Weight (g)": "698",
      "Dimensions (mm)": "L130 x W176",
      "Warranty": "5 years"
    }
  },
  {
    "id": "rspb-avocet-8x32",
    "category": "binoculars",
    "brand": "RSPB",
    "model": "Avocet 8x32",
    "price_gbp": 145,
    "warranty": "5-year warranty",
    "value_for_money": "Strong mid-range value in a lighter format",
    "weight_g": 463,
    "best_for": [
      "Upgrading",
      "Lightweight",
      "All-round birding"
    ],
    "image": "Images/avocet 8x32.jpg",
    "staff_notes": "",
    "specs": {
      "Magnification": "8",
      "Objective lens diameter (mm)": "32",
      "ED lens": "No",
      "Close focus distance": "3-3.5m",
      "Field of view (degrees)": "7.4",
      "Field of view (m/1000m)": "130",
      "Eye relief (mm)": "16.8",
      "Exit pupil (mm)": "4",
      "Waterproof": "Yes",
      "Nitrogen filled": "Yes",
      "Weight (g)": "463",
      "Dimensions (mm)": "L126 x W115",
      "Warranty": "5 years"
    }
  },
  {
    "id": "rspb-avocet-8x42",
    "category": "binoculars",
    "brand": "RSPB",
    "model": "Avocet 8x42",
    "price_gbp": 155,
    "warranty": "5-year warranty",
    "value_for_money": "Strong mid-range value for regular birding",
    "weight_g": 617,
    "best_for": [
      "All-round birding",
      "Upgrading",
      "Regular use"
    ],
    "image": "Images/avocet 8x42.jpg",
    "staff_notes": "",
    "specs": {
      "Magnification": "8",
      "Objective lens diameter (mm)": "42",
      "ED lens": "No",
      "Close focus distance": "3-3.5m",
      "Field of view (degrees)": "6.3",
      "Field of view (m/1000m)": "110",
      "Eye relief (mm)": "20.4",
      "Exit pupil (mm)": "5.2",
      "Waterproof": "Yes",
      "Nitrogen filled": "Yes",
      "Weight (g)": "617",
      "Dimensions (mm)": "L148 x W127",
      "Warranty": "5 years"
    }
  },
  {
    "id": "rspb-avocet-10x42",
    "category": "binoculars",
    "brand": "RSPB",
    "model": "Avocet 10x42",
    "price_gbp": 165,
    "warranty": "5-year warranty",
    "value_for_money": "Strong mid-range value for longer-distance viewing",
    "weight_g": 615,
    "best_for": [
      "Open habitats",
      "Long distance",
      "Upgrading"
    ],
    "image": "Images/avocet 10x42.jpg",
    "staff_notes": "",
    "specs": {
      "Magnification": "10",
      "Objective lens diameter (mm)": "42",
      "ED lens": "No",
      "Close focus distance": "3-3.5m",
      "Field of view (degrees)": "5.8",
      "Field of view (m/1000m)": "101",
      "Eye relief (mm)": "16.9",
      "Exit pupil (mm)": "4.2",
      "Waterproof": "Yes",
      "Nitrogen filled": "Yes",
      "Weight (g)": "615",
      "Dimensions (mm)": "L150 x W127",
      "Warranty": "5 years"
    }
  },
  {
    "id": "rspb-harrier-8x32",
    "category": "binoculars",
    "brand": "RSPB",
    "model": "Harrier 8x32",
    "price_gbp": 230,
    "warranty": "10-year warranty",
    "value_for_money": "Strong value for a lighter carry",
    "weight_g": 509,
    "best_for": [
      "All-round birding",
      "Lightweight"
    ],
    "image": "Images/harrier 8x32.jpg",
    "staff_notes": "",
    "specs": {
      "Magnification": "8",
      "Objective lens diameter (mm)": "32",
      "ED lens": "No",
      "Close focus distance": "2m",
      "Field of view (degrees)": "7.8",
      "Field of view (m/1000m)": "137",
      "Eye relief (mm)": "15.6",
      "Exit pupil (mm)": "4",
      "Waterproof": "Yes",
      "Nitrogen filled": "Yes",
      "Weight (g)": "509",
      "Dimensions (mm)": "L122 x W120",
      "Warranty": "10 years"
    }
  },
  {
    "id": "rspb-harrier-8x42",
    "category": "binoculars",
    "brand": "RSPB",
    "model": "Harrier 8x42",
    "price_gbp": 240,
    "warranty": "10-year warranty",
    "value_for_money": "Strong value for everyday birding",
    "weight_g": 692,
    "best_for": [
      "All-round birding",
      "Upgrading",
      "Open habitats"
    ],
    "image": "Images/harrier 8x42.jpg",
    "staff_notes": "",
    "specs": {
      "Magnification": "8",
      "Objective lens diameter (mm)": "42",
      "ED lens": "No",
      "Close focus distance": "2m",
      "Field of view (degrees)": "8.1",
      "Field of view (m/1000m)": "142",
      "Eye relief (mm)": "17.2",
      "Exit pupil (mm)": "5.25",
      "Waterproof": "Yes",
      "Nitrogen filled": "Yes",
      "Weight (g)": "692",
      "Dimensions (mm)": "L122 x W125",
      "Warranty": "10 years"
    }
  },
  {
    "id": "rspb-harrier-10x42",
    "category": "binoculars",
    "brand": "RSPB",
    "model": "Harrier 10x42",
    "price_gbp": 250,
    "warranty": "10-year warranty",
    "value_for_money": "Affordable option for distance viewing",
    "weight_g": 674,
    "best_for": [
      "Open habitats",
      "Long distance"
    ],
    "image": "Images/harrier 10x42.jpg",
    "staff_notes": "",
    "specs": {
      "Magnification": "10",
      "Objective lens diameter (mm)": "42",
      "ED lens": "No",
      "Close focus distance": "2m",
      "Field of view (degrees)": "6.5",
      "Field of view (m/1000m)": "114",
      "Eye relief (mm)": "15.2",
      "Exit pupil (mm)": "4.2",
      "Waterproof": "Yes",
      "Nitrogen filled": "Yes",
      "Weight (g)": "674",
      "Dimensions (mm)": "L122 x W125",
      "Warranty": "10 years"
    }
  },
  {
    "id": "rspb-harrierx-8x32",
    "category": "binoculars",
    "brand": "RSPB",
    "model": "Harrier X 8x32",
    "price_gbp": 390,
    "warranty": "10-year warranty",
    "value_for_money": "Premium performance in a lighter, more compact format",
    "weight_g": 524,
    "best_for": [
      "Experienced birders",
      "Lightweight",
      "Upgrading"
    ],
    "image": "Images/harrier x 8x32.jpg",
    "staff_notes": "",
    "specs": {
      "Magnification": "8",
      "Objective lens diameter (mm)": "32",
      "ED lens": "Yes",
      "Close focus distance": "2m",
      "Field of view (degrees)": "8.3",
      "Field of view (m/1000m)": "145",
      "Eye relief (mm)": "16.9",
      "Exit pupil (mm)": "4",
      "Waterproof": "Yes",
      "Nitrogen filled": "Yes",
      "Weight (g)": "524",
      "Dimensions (mm)": "L125 x W120",
      "Warranty": "10 years"
    }
  },
  {
    "id": "rspb-harrierx-8x42",
    "category": "binoculars",
    "brand": "RSPB",
    "model": "Harrier X 8x42",
    "price_gbp": 400,
    "warranty": "10-year warranty",
    "value_for_money": "Premium performance with excellent image quality",
    "weight_g": 716,
    "best_for": [
      "Experienced birders",
      "All-round birding",
      "Upgrading"
    ],
    "image": "Images/harrier x 8x42.jpg",
    "staff_notes": "",
    "specs": {
      "Magnification": "8",
      "Objective lens diameter (mm)": "42",
      "ED lens": "Yes",
      "Close focus distance": "2m",
      "Field of view (degrees)": "8.1",
      "Field of view (m/1000m)": "142",
      "Eye relief (mm)": "18.4",
      "Exit pupil (mm)": "5.2",
      "Waterproof": "Yes",
      "Nitrogen filled": "Yes",
      "Weight (g)": "716",
      "Dimensions (mm)": "L143 x W120",
      "Warranty": "10 years"
    }
  },
  {
    "id": "rspb-harrierx-10x42",
    "category": "binoculars",
    "brand": "RSPB",
    "model": "Harrier X 10x42",
    "price_gbp": 410,
    "warranty": "10-year warranty",
    "value_for_money": "Premium clarity and reach for demanding conditions",
    "weight_g": 693,
    "best_for": [
      "Experienced birders",
      "Open habitats",
      "Long distance"
    ],
    "image": "Images/harrier x 10x42.jpg",
    "staff_notes": "",
    "specs": {
      "Magnification": "10",
      "Objective lens diameter (mm)": "42",
      "ED lens": "Yes",
      "Close focus distance": "2m",
      "Field of view (degrees)": "6.6",
      "Field of view (m/1000m)": "116",
      "Eye relief (mm)": "16.7",
      "Exit pupil (mm)": "4.2",
      "Waterproof": "Yes",
      "Nitrogen filled": "Yes",
      "Weight (g)": "693",
      "Dimensions (mm)": "L143 x W120",
      "Warranty": "10 years"
    }
  },
  {
    "id": "rspb-buzzard-8x42",
    "category": "binoculars",
    "brand": "RSPB",
    "model": "Buzzard 8x42",
    "price_gbp": 540,
    "warranty": "10-year warranty",
    "value_for_money": "Premium RSPB optics with outstanding edge-to-edge clarity",
    "weight_g": 740,
    "best_for": [
      "Experienced birders",
      "All-round birding",
      "Low light"
    ],
    "image": "Images/buzzard 8x42.jpg",
    "staff_notes": "",
    "specs": {
      "Magnification": "8x",
      "Objective lens diameter (mm)": "42",
      "ED lens": "Yes",
      "Close focus distance (m)": "2",
      "Field of view (degrees)": "8.1",
      "Field of view (m/1000m)": "142",
      "Eye relief (mm)": "18.4",
      "Exit pupil (mm)": "5.3",
      "Interpupillary distance (mm)": "56-76",
      "Waterproof": "Yes",
      "Nitrogen-filled": "Yes",
      "Weight (g)": "740",
      "Dimensions L x W x H (mm)": "143 x 135 x 53",
      "Warranty": "10 years"
    }
  },
  {
    "id": "rspb-buzzard-10x42",
    "category": "binoculars",
    "brand": "RSPB",
    "model": "Buzzard 10x42",
    "price_gbp": 550,
    "warranty": "10-year warranty",
    "value_for_money": "Premium clarity and reach with edge-to-edge sharpness",
    "weight_g": 715,
    "best_for": [
      "Experienced birders",
      "Open habitats",
      "Long distance"
    ],
    "image": "Images/buzzard 10x42.jpg",
    "staff_notes": "",
    "specs": {
      "Magnification": "10x",
      "Objective lens diameter (mm)": "42",
      "ED lens": "Yes",
      "Close focus distance (m)": "2",
      "Field of view (degrees)": "6.6",
      "Field of view (m/1000m)": "116",
      "Eye relief (mm)": "16.7",
      "Exit pupil (mm)": "4.2",
      "Interpupillary distance (mm)": "56-76",
      "Waterproof": "Yes",
      "Nitrogen-filled": "Yes",
      "Weight (g)": "715",
      "Dimensions L x W x H (mm)": "143 x 135 x 53",
      "Warranty": "10 years"
    }
  },
  {
    "id": "rspb-sparrowhawk-8.5x42",
    "category": "binoculars",
    "brand": "RSPB",
    "model": "Sparrowhawk 8.5x42",
    "price_gbp": 850,
    "warranty": "10-year warranty",
    "value_for_money": "Flagship RSPB binoculars with exceptional clarity and low-light performance",
    "weight_g": 700,
    "best_for": [
      "Experienced birders",
      "All-round birding",
      "Low light"
    ],
    "image": "Images/sparrowhawk 8.5x42.jpg",
    "staff_notes": "",
    "specs": {
      "Magnification": "8.5x",
      "Objective lens diameter (mm)": "42",
      "ED lens": "Yes",
      "Close focus distance (m)": "2",
      "Field of view (degrees)": "8",
      "Field of view (m/1000m)": "140",
      "Eye relief (mm)": "16.7",
      "Exit pupil (mm)": "4.9",
      "Interpupillary distance (mm)": "56-74",
      "Waterproof": "Yes",
      "Nitrogen-filled": "Yes",
      "Weight (g)": "700",
      "Dimensions L x W x H (mm)": "145 x 125 x 50",
      "Warranty": "10 years"
    }
  },
  {
    "id": "rspb-sparrowhawk-10x42",
    "category": "binoculars",
    "brand": "RSPB",
    "model": "Sparrowhawk 10x42",
    "price_gbp": 860,
    "warranty": "10-year warranty",
    "value_for_money": "Flagship optics offering outstanding reach and edge-to-edge sharpness",
    "weight_g": 700,
    "best_for": [
      "Experienced birders",
      "Open habitats",
      "Long distance"
    ],
    "image": "Images/sparrowhawk 10x42.jpg",
    "staff_notes": "",
    "specs": {
      "Magnification": "10x",
      "Objective lens diameter (mm)": "42",
      "ED lens": "Yes",
      "Close focus distance (m)": "1.5",
      "Field of view (degrees)": "6.6",
      "Field of view (m/1000m)": "115",
      "Eye relief (mm)": "17.8",
      "Exit pupil (mm)": "4.2",
      "Interpupillary distance (mm)": "56-74",
      "Waterproof": "Yes",
      "Nitrogen-filled": "Yes",
      "Weight (g)": "700",
      "Dimensions L x W x H (mm)": "145 x 125 x 50",
      "Warranty": "10 years"
    }
  }
]